Workbook
Name Slicer_Critical_Skill: #N/A
Name Slicer_Department: #N/A
Name Slicer_Exit_Reason: #N/A
Name Slicer_Job_Satisfaction: #N/A
Name Slicer_Salary_Grade: #N/A

Sheet Dashboard

Sheet Sheet2
A3: Row Labels | B3: Sum of Age | C3: Sum of KPI Achievement % | D3: Sum of Training Hours | E3: Sum of Goal Completion %
A4: Data Analyst | B4: 281 | C4: 641 | D4: 223 | E4: 695
A5: DevOps Engineer | B5: 392 | C5: 845 | D5: 405 | E5: 796
A6: QA Engineer | B6: 127 | C6: 339 | D6: 112 | E6: 309
A7: Software Engineer | B7: 179 | C7: 392 | D7: 164 | E7: 428
A8: System Administrator | B8: 103 | C8: 256 | D8: 80 | E8: 231
A9: UI/UX Designer | B9: 478 | C9: 873 | D9: 353 | E9: 838
A10: Grand Total | B10: 1560 | C10: 3346 | D10: 1337 | E10: 3297
A23: Row Labels | B23: Sum of Work-Life Balance | C23: Sum of Years at Company | D23: Sum of Monthly Salary | E23: Sum of Job Satisfaction
A24: Administration | B24: 14 | C24: 28.5 | D24: 575248 | E24: 14
A25: Customer Support | B25: 18 | C25: 30.3 | D25: 550568 | E25: 14
A26: Finance | B26: 22 | C26: 39.8 | D26: 566336 | E26: 14
A27: HR | B27: 34 | C27: 39.1 | D27: 998159 | E27: 24
A28: IT | B28: 36 | C28: 45.8 | D28: 807176 | E28: 22
A29: Logistics | B29: 27 | C29: 51.6 | D29: 863148 | E29: 20
A30: Marketing | B30: 32 | C30: 47.5 | D30: 821658 | E30: 22
A31: Operations | B31: 27 | C31: 32.3 | D31: 716814 | E31: 22
A32: R&D | B32: 42 | C32: 69.3 | D32: 935603 | E32: 26
A33: Sales | B33: 40 | C33: 38.7 | D33: 861583 | E33: 20
A34: Grand Total | B34: 292 | C34: 422.9 | D34: 7696293 | E34: 198
A40: Row Labels | B40: Sum of Job Satisfaction | C40: Sum of Years at Company | D40: Sum of Work-Life Balance
A41: No | B41: 9 | C41: 8.9 | D41: 7
A42: Exited | B42: 9 | C42: 8.9 | D42: 7
A43: Yes | B43: 13 | C43: 16.2 | D43: 7
A44: Exited | B44: 13 | C44: 16.2 | D44: 7
A45: Grand Total | B45: 22 | C45: 25.1 | D45: 14
A61: Row Labels | B61: Sum of Experience (Years) | C61: Sum of Monthly Salary | D61: Sum of Total Compensation | E61: Sum of Last Increment %
A62: Account Manager | B62: 8.3 | C62: 196517 | D62: 2637553 | E62: 8.1
A63: Admin Executive | B63: 4.6 | C63: 89524 | D63: 1137671 | E63: 6.8
A64: Operations Executive | B64: 13.5 | C64: 124064 | D64: 1699548 | E64: 22.2
A65: System Administrator | B65: 11.4 | C65: 142773 | D65: 1990546 | E65: 18.7
A66: Training Specialist | B66: 21.2 | C66: 390856 | D66: 5198643 | E66: 41.5
A67: Grand Total | B67: 59 | C67: 943734 | D67: 12663961 | E67: 97.3
A80: Row Labels | B80: Count of Training Need
A81: AI / ML | B81: 18
A82: High | B82: 10
A83: Low | B83: 3
A84: Medium | B84: 5
A85: Grand Total | B85: 18

Sheet M1_Performance
A1: Employee ID | B1: Employee Name | C1: Department | D1: Job Role | E1: Gender | F1: Age | G1: Performance Score | H1: Productivity % | I1: KPI Achievement % | J1: Goal Completion % | K1: Training Hours | L1: Review Rating | M1: Review Year
A2: EMP00001 | B2: Ram Gupta | C2: HR | D2: HR Executive | E2: Female | F2: 36 | G2: 3.44 | H2: 85 | I2: 66 | J2: 68 | K2: 46 | L2: Very Good | M2: 2026
A3: EMP00002 | B3: Rohan Rao | C3: R&D | D3: Research Analyst | E3: Female | F3: 23 | G3: 4.8 | H3: 74 | I3: 78 | J3: 77 | K3: 30 | L3: Average | M3: 2026
A4: EMP00003 | B4: Yash Upadhyay | C4: R&D | D4: Research Analyst | E4: Male | F4: 55 | G4: 2.97 | H4: 100 | I4: 91 | J4: 98 | K4: 32 | L4: Needs Improvement | M4: 2026
A5: EMP00004 | B5: Aryan Joshi | C5: Sales | D5: Sales Executive | E5: Male | F5: 48 | G5: 2.34 | H5: 77 | I5: 67 | J5: 79 | K5: 12 | L5: Needs Improvement | M5: 2024
A6: EMP00005 | B6: Karan Kapoor | C6: Operations | D6: Operations Executive | E6: Male | F6: 45 | G6: 3.81 | H6: 77 | I6: 64 | J6: 99 | K6: 11 | L6: Good | M6: 2024
A7: EMP00006 | B7: Vikram Malhotra | C7: Logistics | D7: Warehouse Manager | E7: Male | F7: 50 | G7: 4.67 | H7: 87 | I7: 85 | J7: 90 | K7: 11 | L7: Average | M7: 2026
A8: EMP00007 | B8: Rinku Verma | C8: HR | D8: Payroll Executive | E8: Female | F8: 44 | G8: 4.51 | H8: 79 | I8: 91 | J8: 78 | K8: 15 | L8: Average | M8: 2025
A9: EMP00008 | B9: Karan Gupta | C9: IT | D9: System Administrator | E9: Male | F9: 39 | G9: 3.98 | H9: 100 | I9: 78 | J9: 65 | K9: 11 | L9: Average | M9: 2026
A10: EMP00009 | B10: Nisha Joshi | C10: Customer Support | D10: Customer Success Analyst | E10: Female | F10: 44 | G10: 4.74 | H10: 92 | I10: 79 | J10: 80 | K10: 15 | L10: Good | M10: 2026
A11: EMP00010 | B11: Yash Malhotra | C11: Sales | D11: Sales Executive | E11: Male | F11: 55 | G11: 2.39 | H11: 73 | I11: 81 | J11: 94 | K11: 14 | L11: Needs Improvement | M11: 2026
A12: EMP00011 | B12: Arun Singh | C12: Sales | D12: Sales Analyst | E12: Male | F12: 41 | G12: 3.53 | H12: 83 | I12: 61 | J12: 76 | K12: 21 | L12: Needs Improvement | M12: 2024
A13: EMP00012 | B13: Neha Tiwari | C13: Operations | D13: Operations Analyst | E13: Female | F13: 25 | G13: 4.1 | H13: 62 | I13: 98 | J13: 87 | K13: 35 | L13: Excellent | M13: 2024
... A501: EMP00500 | B501: Diya Dwivedi | C501: R&D | D501: Research Analyst | E501: Male | F501: 51 | G501: 2.27 | H501: 68 | I501: 80 | J501: 100 | K501: 35 | L501: Excellent | M501: 2025

Sheet M2_Attrition
A1: Employee ID | B1: Employee Name | C1: Department | D1: Job Role | E1: Gender | F1: Age | G1: Monthly Salary | H1: Years at Company | I1: Job Satisfaction | J1: Work-Life Balance | K1: Overtime | L1: Attrition Status | M1: Exit Reason | N1: Exit Date
A2: EMP00001 | B2: Ram Gupta | C2: HR | D2: HR Executive | E2: Female | F2: 36 | G2: 46289 | H2: 5.2 | I2: 2 | J2: 2 | K2: Yes | L2: Active
A3: EMP00002 | B3: Rohan Rao | C3: R&D | D3: Research Analyst | E3: Female | F3: 23 | G3: 40280 | H3: 7.4 | I3: 5 | J3: 4 | K3: Yes | L3: Active
A4: EMP00003 | B4: Yash Upadhyay | C4: R&D | D4: Research Analyst | E4: Male | F4: 55 | G4: 56893 | H4: 3 | I4: 4 | J4: 2 | K4: No | L4: Active
A5: EMP00004 | B5: Aryan Joshi | C5: Sales | D5: Sales Executive | E5: Male | F5: 48 | G5: 64421 | H5: 3.9 | I5: 2 | J5: 1 | K5: Yes | L5: Active
A6: EMP00005 | B6: Karan Kapoor | C6: Operations | D6: Operations Executive | E6: Male | F6: 45 | G6: 75052 | H6: 6.7 | I6: 5 | J6: 4 | K6: Yes | L6: Exited | M6: Better Opportunity | N6: 45469
A7: EMP00006 | B7: Vikram Malhotra | C7: Logistics | D7: Warehouse Manager | E7: Male | F7: 50 | G7: 44361 | H7: 1.7 | I7: 4 | J7: 1 | K7: No | L7: Active
A8: EMP00007 | B8: Rinku Verma | C8: HR | D8: Payroll Executive | E8: Female | F8: 44 | G8: 53203 | H8: 1.3 | I8: 5 | J8: 3 | K8: Yes | L8: Active
A9: EMP00008 | B9: Karan Gupta | C9: IT | D9: System Administrator | E9: Male | F9: 39 | G9: 58512 | H9: 6.9 | I9: 4 | J9: 3 | K9: No | L9: Active
A10: EMP00009 | B10: Nisha Joshi | C10: Customer Support | D10: Customer Success Analyst | E10: Female | F10: 44 | G10: 76520 | H10: 5.9 | I10: 5 | J10: 2 | K10: Yes | L10: Exited | M10: Career Growth | N10: 45302
A11: EMP00010 | B11: Yash Malhotra | C11: Sales | D11: Sales Executive | E11: Male | F11: 55 | G11: 49417 | H11: 5 | I11: 3 | J11: 3 | K11: No | L11: Active
A12: EMP00011 | B12: Arun Singh | C12: Sales | D12: Sales Analyst | E12: Male | F12: 41 | G12: 58021 | H12: 7.1 | I12: 4 | J12: 1 | K12: Yes | L12: Active
A13: EMP00012 | B13: Neha Tiwari | C13: Operations | D13: Operations Analyst | E13: Female | F13: 25 | G13: 102341 | H13: 5.4 | I13: 2 | J13: 5 | K13: Yes | L13: Active
A14: EMP00013 | B14: Aryan Rao | C14: Marketing | D14: Brand Manager | E14: Female | F14: 50 | G14: 62718 | H14: 6.1 | I14: 2 | J14: 3 | K14: Yes | L14: Active
A15: EMP00014 | B15: Ishita Kumar | C15: R&D | D15: Product Researcher | E15: Female | F15: 58 | G15: 75447 | H15: 3.3 | I15: 1 | J15: 2 | K15: No | L15: Active
A16: EMP00015 | B16: Anshul Patel | C16: R&D | D16: Innovation Analyst | E16: Male | F16: 24 | G16: 48033 | H16: 6.5 | I16: 4 | J16: 3 | K16: No | L16: Active
A17: EMP00016 | B17: Rahul Khan | C17: Customer Support | D17: Support Executive | E17: Female | F17: 45 | G17: 89348 | H17: 1.1 | I17: 5 | J17: 3 | K17: No | L17: Active
A18: EMP00017 | B18: Vihaan Gupta | C18: R&D | D18: Research Analyst | E18: Male | F18: 55 | G18: 112012 | H18: 4.8 | I18: 5 | J18: 4 | K18: Yes | L18: Active
A19: EMP00018 | B19: Neha Khan | C19: Sales | D19: Account Manager | E19: Male | F19: 50 | G19: 122646 | H19: 7.7 | I19: 5 | J19: 2 | K19: Yes | L19: Active
A20: EMP00019 | B20: Rohan Kumar | C20: R&D | D20: Research Engineer | E20: Male | F20: 40 | G20: 107818 | H20: 2.1 | I20: 3 | J20: 5 | K20: No | L20: Active
A21: EMP00020 | B21: Ananya Kapoor | C21: Operations | D21: Operations Manager | E21: Male | F21: 41 | G21: 30552 | H21: 2.3 | I21: 3 | J21: 4 | K21: No | L21: Active
A22: EMP00021 | B22: Arjun Sethi | C22: Sales | D22: Sales Manager | E22: Male | F22: 36 | G22: 38322 | H22: 1.4 | I22: 1 | J22: 2 | K22: No | L22: Exited | M22: Relocation | N22: 45501
A23: EMP00022 | B23: Diya Khan | C23: HR | D23: Payroll Executive | E23: Male | F23: 29 | G23: 100063 | H23: 2.4 | I23: 2 | J23: 2 | K23: No | L23: Active
A24: EMP00023 | B24: Meera Malhotra | C24: R&D | D24: Innovation Analyst | E24: Male | F24: 55 | G24: 121447 | H24: 5.5 | I24: 2 | J24: 1 | K24: Yes | L24: Active
A25: EMP00024 | B25: Arjun Tiwari | C25: Operations | D25: Operations Analyst | E25: Female | F25: 28 | G25: 57451 | H25: 5 | I25: 4 | J25: 3 | K25: Yes | L25: Active
A26: EMP00025 | B26: Arjun Singh | C26: IT | D26: UI/UX Designer | E26: Male | F26: 58 | G26: 28942 | H26: 5.3 | I26: 2 | J26: 1 | K26: Yes | L26: Active
A27: EMP00026 | B27: Ishita Khan | C27: Marketing | D27: Marketing Executive | E27: Male | F27: 42 | G27: 95391 | H27: 7 | I27: 4 | J27: 5 | K27: No | L27: Active
A28: EMP00027 | B28: Ishita Sethi | C28: Administration | D28: Office Manager | E28: Male | F28: 57 | G28: 89953 | H28: 1.3 | I28: 4 | J28: 5 | K28: Yes | L28: Exited | M28: Work Pressure | N28: 46102
A29: EMP00028 | B29: Sara Nair | C29: Customer Support | D29: Support Manager | E29: Male | F29: 27 | G29: 74438 | H29: 2.9 | I29: 2 | J29: 5 | K29: No | L29: Active
A30: EMP00029 | B30: Vihaan Gupta | C30: Administration | D30: Admin Executive | E30: Male | F30: 24 | G30: 123448 | H30: 3.2 | I30: 5 | J30: 1 | K30: Yes | L30: Active
A31: EMP00030 | B31: Sara Patel | C31: Marketing | D31: SEO Specialist | E31: Male | F31: 55 | G31: 46373 | H31: 2.7 | I31: 1 | J31: 4 | K31: No | L31: Active
A32: EMP00031 | B32: Ananya Singh | C32: Sales | D32: Account Manager | E32: Male | F32: 25 | G32: 100132 | H32: 2.8 | I32: 1 | J32: 4 | K32: No | L32: Active
A33: EMP00032 | B33: Pooja Sethi | C33: R&D | D33: Research Analyst | E33: Male | F33: 36 | G33: 81269 | H33: 5.9 | I33: 1 | J33: 3 | K33: Yes | L33: Active
A34: EMP00033 | B34: Aditya Khan | C34: Marketing | D34: Brand Manager | E34: Male | F34: 31 | G34: 28282 | H34: 3.5 | I34: 1 | J34: 2 | K34: Yes | L34: Active
A35: EMP00034 | B35: Rohan Mehta | C35: Administration | D35: Admin Assistant | E35: Female | F35: 56 | G35: 48289 | H35: 2.3 | I35: 3 | J35: 1 | K35: Yes | L35: Active
A36: EMP00035 | B36: Aman Sethi | C36: Marketing | D36: Marketing Executive | E36: Male | F36: 41 | G36: 34572 | H36: 7.1 | I36: 5 | J36: 5 | K36: No | L36: Active
A37: EMP00036 | B37: Arjun Dwivedi | C37: R&D | D37: Research Engineer | E37: Male | F37: 53 | G37: 52356 | H37: 6.8 | I37: 3 | J37: 2 | K37: No | L37: Active
A38: EMP00037 | B38: Aman Dwivedi | C38: HR | D38: Recruiter | E38: Female | F38: 28 | G38: 60271 | H38: 1.4 | I38: 2 | J38: 2 | K38: Yes | L38: Active
A39: EMP00038 | B39: Rahul Tiwari | C39: IT | D39: UI/UX Designer | E39: Male | F39: 47 | G39: 102085 | H39: 1.2 | I39: 2 | J39: 5 | K39: Yes | L39: Exited | M39: Compensation | N39: 45308
A40: EMP00039 | B40: Aryan Mehta | C40: Sales | D40: Sales Manager | E40: Female | F40: 36 | G40: 79876 | H40: 4.8 | I40: 3 | J40: 4 | K40: Yes | L40: Active
A41: EMP00040 | B41: Aman Gupta | C41: Administration | D41: Admin Assistant | E41: Male | F41: 21 | G41: 109416 | H41: 2.6 | I41: 1 | J41: 2 | K41: Yes | L41: Active
A42: EMP00041 | B42: Vikram Kapoor | C42: HR | D42: Payroll Executive | E42: Male | F42: 53 | G42: 45361 | H42: 4.8 | I42: 3 | J42: 4 | K42: No | L42: Active
A43: EMP00042 | B43: Arun Mishra | C43: HR | D43: Recruiter | E43: Female | F43: 39 | G43: 85433 | H43: 6 | I43: 1 | J43: 4 | K43: No | L43: Active
A44: EMP00043 | B44: Ananya Kumar | C44: Sales | D44: Sales Analyst | E44: Male | F44: 56 | G44: 114951 | H44: 4.4 | I44: 1 | J44: 4 | K44: No | L44: Active
A45: EMP00044 | B45: Meera Dwivedi | C45: Sales | D45: Sales Executive | E45: Male | F45: 56 | G45: 63697 | H45: 6 | I45: 4 | J45: 5 | K45: No | L45: Active
A46: EMP00045 | B46: Kabir Singh | C46: Marketing | D46: Content Strategist | E46: Male | F46: 37 | G46: 92032 | H46: 2.1 | I46: 3 | J46: 2 | K46: Yes | L46: Active
A47: EMP00046 | B47: Lakhan Kumar | C47: HR | D47: HR Manager | E47: Female | F47: 23 | G47: 71719 | H47: 7.7 | I47: 3 | J47: 2 | K47: Yes | L47: Exited | M47: Compensation | N47: 46217
A48: EMP00047 | B48: Aarav Gupta | C48: Sales | D48: Sales Manager | E48: Female | F48: 56 | G48: 101519 | H48: 3 | I48: 2 | J48: 5 | K48: No | L48: Active
A49: EMP00048 | B49: Aryan Nair | C49: HR | D49: Recruiter | E49: Male | F49: 44 | G49: 100420 | H49: 1.2 | I49: 2 | J49: 2 | K49: Yes | L49: Active
A50: EMP00049 | B50: Rohan Rao | C50: Finance | D50: Financial Analyst | E50: Female | F50: 44 | G50: 74898 | H50: 7.3 | I50: 2 | J50: 1 | K50: Yes | L50: Active
A51: EMP00050 | B51: Divyansh Patel | C51: HR | D51: Training Specialist | E51: Female | F51: 30 | G51: 49299 | H51: 5.1 | I51: 4 | J51: 1 | K51: Yes | L51: Active
A52: EMP00051 | B52: Karan Rao | C52: Customer Support | D52: Support Executive | E52: Male | F52: 42 | G52: 115806 | H52: 3.1 | I52: 2 | J52: 2 | K52: Yes | L52: Active
A53: EMP00052 | B53: Ishita Joshi | C53: Sales | D53: Sales Manager | E53: Male | F53: 45 | G53: 89694 | H53: 7.3 | I53: 3 | J53: 1 | K53: No | L53: Active
A54: EMP00053 | B54: Govind Joshi | C54: Administration | D54: Admin Assistant | E54: Female | F54: 35 | G54: 31101 | H54: 5.2 | I54: 4 | J54: 3 | K54: No | L54: Active
A55: EMP00054 | B55: Anshul Chauhan | C55: Customer Support | D55: Customer Success Analyst | E55: Female | F55: 25 | G55: 74025 | H55: 4.6 | I55: 1 | J55: 4 | K55: No | L55: Active
A56: EMP00055 | B56: Aman Khan | C56: Customer Support | D56: Customer Success Analyst | E56: Male | F56: 28 | G56: 51405 | H56: 4.8 | I56: 3 | J56: 4 | K56: Yes | L56: Active
A57: EMP00056 | B57: Satyam Chauhan | C57: IT | D57: Software Engineer | E57: Female | F57: 43 | G57: 85199 | H57: 4.2 | I57: 5 | J57: 2 | K57: No | L57: Exited | M57: Personal Reasons | N57: 45660
A58: EMP00057 | B58: Sara Sharma | C58: HR | D58: HR Manager | E58: Male | F58: 37 | G58: 120901 | H58: 7.2 | I58: 5 | J58: 4 | K58: Yes | L58: Active
A59: EMP00058 | B59: Vikram Tiwari | C59: R&D | D59: Research Engineer | E59: Female | F59: 48 | G59: 115062 | H59: 7 | I59: 4 | J59: 2 | K59: No | L59: Active
A60: EMP00059 | B60: Govind Nair | C60: Logistics | D60: Warehouse Manager | E60: Male | F60: 40 | G60: 68538 | H60: 2.1 | I60: 1 | J60: 2 | K60: Yes | L60: Active
A61: EMP00060 | B61: Sara Malhotra | C61: Operations | D61: Operations Analyst | E61: Female | F61: 56 | G61: 53144 | H61: 6.3 | I61: 1 | J61: 5 | K61: No | L61: Active
A62: EMP00061 | B62: Meera Mehta | C62: Finance | D62: Auditor | E62: Female | F62: 46 | G62: 28053 | H62: 1.6 | I62: 5 | J62: 3 | K62: No | L62: Active
A63: EMP00062 | B63: Govind Joshi | C63: Marketing | D63: Brand Manager | E63: Female | F63: 50 | G63: 85954 | H63: 2.8 | I63: 2 | J63: 2 | K63: No | L63: Active
A64: EMP00063 | B64: Govind Dwivedi | C64: R&D | D64: Innovation Analyst | E64: Male | F64: 26 | G64: 95561 | H64: 4.6 | I64: 2 | J64: 4 | K64: Yes | L64: Active
A65: EMP00064 | B65: Aryan Sharma | C65: Operations | D65: Operations Executive | E65: Male | F65: 40 | G65: 54100 | H65: 5.2 | I65: 1 | J65: 2 | K65: Yes | L65: Exited | M65: Better Opportunity | N65: 45340
A66: EMP00065 | B66: Neha Upadhyay | C66: IT | D66: Data Analyst | E66: Female | F66: 25 | G66: 82321 | H66: 2.6 | I66: 5 | J66: 4 | K66: Yes | L66: Active
A67: EMP00066 | B67: Anshul Sharma | C67: Marketing | D67: Brand Manager | E67: Female | F67: 46 | G67: 47342 | H67: 5 | I67: 3 | J67: 5 | K67: No | L67: Active
A68: EMP00067 | B68: Aditi Mishra | C68: HR | D68: HR Manager | E68: Male | F68: 32 | G68: 88889 | H68: 1.9 | I68: 5 | J68: 1 | K68: Yes | L68: Active
A69: EMP00068 | B69: Rahul Mishra | C69: Marketing | D69: Marketing Executive | E69: Female | F69: 29 | G69: 115500 | H69: 2.5 | I69: 1 | J69: 4 | K69: No | L69: Active
A70: EMP00069 | B70: Yash Patel | C70: Logistics | D70: Warehouse Manager | E70: Female | F70: 53 | G70: 99810 | H70: 3 | I70: 2 | J70: 5 | K70: Yes | L70: Active
A71: EMP00070 | B71: Pooja Rao | C71: Administration | D71: Facility Coordinator | E71: Female | F71: 36 | G71: 96327 | H71: 4.6 | I71: 5 | J71: 5 | K71: No | L71: Active
A72: EMP00071 | B72: Vihaan Tiwari | C72: Sales | D72: Account Manager | E72: Male | F72: 39 | G72: 63614 | H72: 5.1 | I72: 2 | J72: 5 | K72: No | L72: Active
A73: EMP00072 | B73: Rinku Kumar | C73: R&D | D73: Research Analyst | E73: Male | F73: 30 | G73: 78205 | H73: 5.2 | I73: 1 | J73: 4 | K73: Yes | L73: Active
A74: EMP00073 | B74: Yash Nair | C74: Marketing | D74: Marketing Executive | E74: Female | F74: 47 | G74: 99121 | H74: 4 | I74: 2 | J74: 4 | K74: No | L74: Active
A75: EMP00074 | B75: Aarav Upadhyay | C75: IT | D75: Data Analyst | E75: Female | F75: 45 | G75: 119163 | H75: 1.2 | I75: 2 | J75: 2 | K75: No | L75: Active
A76: EMP00075 | B76: Karan Nair | C76: Customer Support | D76: Service Executive | E76: Male | F76: 43 | G76: 79116 | H76: 4.4 | I76: 1 | J76: 3 | K76: No | L76: Active
A77: EMP00076 | B77: Pooja Sharma | C77: R&D | D77: Research Engineer | E77: Female | F77: 35 | G77: 85125 | H77: 4.7 | I77: 1 | J77: 4 | K77: Yes | L77: Active
... A81: EMP00080 | B81: Pooja Sharma | C81: Operations | D81: Operations Analyst | E81: Female | F81: 47 | G81: 38735 | H81: 4.9 | I81: 4 | J81: 1 | K81: No | L81: Active
A82: EMP00081 | B82: Aditi Sharma | C82: R&D | D82: Research Analyst | E82: Female | F82: 35 | G82: 113426 | H82: 7 | I82: 5 | J82: 4 | K82: No | L82: Exited | M82: Career Growth | N82: 45767
A83: EMP00082 | B83: Pooja Gupta | C83: Marketing | D83: SEO Specialist | E83: Male | F83: 30 | G83: 44544 | H83: 5.1 | I83: 2 | J83: 1 | K83: No | L83: Active
A84: EMP00083 | B84: Satyam Dwivedi | C84: Logistics | D84: Supply Chain Analyst | E84: Female | F84: 37 | G84: 49992 | H84: 3.6 | I84: 4 | J84: 5 | K84: No | L84: Active
A85: EMP00084 | B85: Vikram Mehta | C85: HR | D85: Recruiter | E85: Female | F85: 27 | G85: 31365 | H85: 1.3 | I85: 3 | J85: 2 | K85: No | L85: Active
A86: EMP00085 | B86: Rinku Rao | C86: Logistics | D86: Transport Coordinator | E86: Female | F86: 33 | G86: 105607 | H86: 6.9 | I86: 5 | J86: 2 | K86: No | L86: Active
A87: EMP00086 | B87: Riya Nair | C87: HR | D87: Training Specialist | E87: Male | F87: 57 | G87: 73508 | H87: 7.3 | I87: 2 | J87: 2 | K87: No | L87: Active
A88: EMP00087 | B88: Ananya Nair | C88: Operations | D88: Operations Executive | E88: Female | F88: 21 | G88: 92251 | H88: 3 | I88: 3 | J88: 2 | K88: No | L88: Active
A89: EMP00088 | B89: Rahul Khan | C89: Operations | D89: Operations Analyst | E89: Male | F89: 48 | G89: 124180 | H89: 5.8 | I89: 4 | J89: 3 | K89: Yes | L89: Active
A90: EMP00089 | B90: Vihaan Rao | C90: Logistics | D90: Transport Coordinator | E90: Female | F90: 48 | G90: 63179 | H90: 1.1 | I90: 3 | J90: 5 | K90: Yes | L90: Exited | M90: Higher Studies | N90: 45374
A91: EMP00090 | B91: Satyam Malhotra | C91: HR | D91: Training Specialist | E91: Female | F91: 36 | G91: 102691 | H91: 2.5 | I91: 3 | J91: 5 | K91: Yes | L91: Active
A92: EMP00091 | B92: Rohan Kapoor | C92: Operations | D92: Operations Executive | E92: Female | F92: 41 | G92: 91904 | H92: 5.7 | I92: 5 | J92: 2 | K92: Yes | L92: Active
A93: EMP00092 | B93: Rahul Joshi | C93: Sales | D93: Business Development Executive | E93: Female | F93: 38 | G93: 29330 | H93: 1.5 | I93: 5 | J93: 2 | K93: Yes | L93: Active
A94: EMP00093 | B94: Rinku Sethi | C94: HR | D94: Recruiter | E94: Female | F94: 52 | G94: 59499 | H94: 1.5 | I94: 1 | J94: 1 | K94: No | L94: Active
A95: EMP00094 | B95: Aditya Rao | C95: Administration | D95: Facility Coordinator | E95: Male | F95: 26 | G95: 57045 | H95: 4.4 | I95: 4 | J95: 2 | K95: Yes | L95: Active
A96: EMP00095 | B96: Nisha Nair | C96: Sales | D96: Sales Analyst | E96: Female | F96: 51 | G96: 97588 | H96: 1.5 | I96: 3 | J96: 3 | K96: No | L96: Active
A97: EMP00096 | B97: Kabir Rao | C97: R&D | D97: Product Researcher | E97: Female | F97: 50 | G97: 68189 | H97: 4.7 | I97: 2 | J97: 4 | K97: Yes | L97: Active
A98: EMP00097 | B98: Diya Joshi | C98: HR | D98: Recruiter | E98: Female | F98: 28 | G98: 118461 | H98: 1.7 | I98: 2 | J98: 5 | K98: No | L98: Active
A99: EMP00098 | B99: Meera Gupta | C99: Marketing | D99: Brand Manager | E99: Female | F99: 58 | G99: 106222 | H99: 1.9 | I99: 2 | J99: 1 | K99: No | L99: Active
A100: EMP00099 | B100: Aarav Mishra | C100: Marketing | D100: Content Strategist | E100: Male | F100: 44 | G100: 67618 | H100: 5.7 | I100: 3 | J100: 3 | K100: Yes | L100: Active
A101: EMP00100 | B101: Rinku Kumar | C101: Finance | D101: Finance Manager | E101: Male | F101: 24 | G101: 66290 | H101: 1.5 | I101: 5 | J101: 3 | K101: Yes | L101: Active
A102: EMP00101 | B102: Pooja Das | C102: Administration | D102: Admin Executive | E102: Male | F102: 57 | G102: 89524 | H102: 4.6 | I102: 1 | J102: 2 | K102: Yes | L102: Exited | M102: Personal Reasons | N102: 45879
A103: EMP00102 | B103: Arun Verma | C103: Operations | D103: Operations Manager | E103: Male | F103: 37 | G103: 42953 | H103: 2.4 | I103: 2 | J103: 1 | K103: Yes | L103: Active
...

Sheet M3_Recruitment
A1: Application ID | B1: Application Date | C1: Candidate Name | D1: Department | E1: Job Role | F1: Source | G1: Experience (Years) | H1: Education | I1: Screening Score | J1: Interview Score | K1: Stage | L1: Offer Status | M1: Days to Hire | N1: Recruiter
A2: APP00001 | B2: 46052 | C2: Rohan Joshi | D2: Logistics | E2: Transport Coordinator | F2: LinkedIn | G2: 7 | H2: MBA | I2: 67 | J2: 77 | K2: Hired | L2: Accepted | M2: 43 | N2: Recruiter A
A3: APP00002 | B3: 45986 | C3: Rohan Khan | D3: Administration | E3: Admin Executive | F3: Company Website | G3: 0 | H3: MCA | I3: 66 | J3: 74 | K3: Applied | L3: N/A | N3: Recruiter E
A4: APP00003 | B4: 46014 | C4: Riya Kapoor | D4: HR | E4: Payroll Executive | F4: LinkedIn | G4: 6 | H4: Diploma | I4: 65 | J4: 68 | K4: Offered | L4: Pending | N4: Recruiter B
A5: APP00004 | B5: 46265 | C5: Diya Malhotra | D5: Marketing | E5: Digital Marketing Analyst | F5: Employee Referral | G5: 12 | H5: MCA | I5: 93 | J5: 72 | K5: Applied | L5: N/A | N5: Recruiter B
A6: APP00005 | B6: 46151 | C6: Vihaan Mishra | D6: HR | E6: HR Manager | F6: Consultancy | G6: 5 | H6: Diploma | I6: 80 | J6: 42 | K6: Applied | L6: N/A | N6: Recruiter D
A7: APP00006 | B7: 46277 | C7: Rohan Sharma | D7: Customer Support | E7: Service Executive | F7: LinkedIn | G7: 3 | H7: Other | I7: 45 | J7: 92 | K7: Rejected | L7: N/A | N7: Recruiter E
A8: APP00007 | B8: 45819 | C8: Aman Mishra | D8: Operations | E8: Operations Manager | F8: Consultancy | G8: 7 | H8: MCA | I8: 56 | J8: 70 | K8: Hired | L8: Accepted | M8: 37 | N8: Recruiter B
A9: APP00008 | B9: 45729 | C9: Diya Tiwari | D9: Sales | E9: Business Development Executive | F9: LinkedIn | G9: 10 | H9: Other | I9: 68 | J9: 91 | K9: Hired | L9: Accepted | M9: 13 | N9: Recruiter E
A10: APP00009 | B10: 46094 | C10: Yash Joshi | D10: Operations | E10: Process Analyst | F10: Job Portal | G10: 1 | H10: B.Tech | I10: 60 | J10: 40 | K10: Rejected | L10: N/A | N10: Recruiter E
A11: APP00010 | B11: 45666 | C11: Riya Patel | D11: Administration | E11: Office Manager | F11: Employee Referral | G11: 10 | H11: Other | I11: 74 | J11: 88 | K11: Rejected | L11: N/A | N11: Recruiter D
A12: APP00011 | B12: 45776 | C12: Vihaan Kumar | D12: Administration | E12: Facility Coordinator | F12: Social Media | G12: 1 | H12: MCA | I12: 93 | J12: 72 | K12: Screened | L12: N/A | N12: Recruiter D
A13: APP00012 | B13: 45861 | C13: Yash Verma | D13: R&D | E13: Innovation Analyst | F13: LinkedIn | G13: 0 | H13: Graduate | I13: 94 | J13: 78 | K13: Applied | L13: N/A | N13: Recruiter A
A14: APP00013 | B14: 45802 | C14: Rohan Singh | D14: Finance | E14: Finance Manager | F14: Company Website | G14: 3 | H14: MCA | I14: 63 | J14: 83 | K14: Screened | L14: N/A | N14: Recruiter D
A15: APP00014 | B15: 45754 | C15: Rinku Nair | D15: Administration | E15: Facility Coordinator | F15: Job Portal | G15: 12 | H15: MCA | I15: 84 | J15: 93 | K15: Rejected | L15: N/A | N15: Recruiter E
A16: APP00015 | B16: 45768 | C16: Nisha Malhotra | D16: Logistics | E16: Transport Coordinator | F16: Employee Referral | G16: 6 | H16: Other | I16: 68 | J16: 85 | K16: Interviewed | L16: N/A | N16: Recruiter D
A17: APP00016 | B17: 45699 | C17: Rahul Rao | D17: Customer Support | E17: Customer Success Analyst | F17: LinkedIn | G17: 9 | H17: Diploma | I17: 84 | J17: 86 | K17: Offered | L17: Pending | N17: Recruiter C
A18: APP00017 | B18: 46033 | C18: Meera Kumar | D18: IT | E18: Software Engineer | F18: Social Media | G18: 2 | H18: MBA | I18: 55 | J18: 99 | K18: Rejected | L18: N/A | N18: Recruiter C
A19: APP00018 | B19: 45863 | C19: Aman Verma | D19: Marketing | E19: Brand Manager | F19: Consultancy | G19: 11 | H19: Diploma | I19: 56 | J19: 48 | K19: Rejected | L19: N/A | N19: Recruiter B
A20: APP00019 | B20: 46127 | C20: Govind Rao | D20: Logistics | E20: Logistics Executive | F20: Employee Referral | G20: 0 | H20: Graduate | I20: 68 | J20: 84 | K20: Screened | L20: N/A | N20: Recruiter A
A21: APP00020 | B21: 46258 | C21: Aditi Gupta | D21: Operations | E21: Operations Analyst | F21: Job Portal | G21: 1 | H21: Graduate | I21: 50 | J21: 98 | K21: Rejected | L21: N/A | N21: Recruiter D
... A28: APP00027 | B28: 45660 | C28: Ram Kumar | D28: Finance | E28: Finance Manager | F28: Job Portal | G28: 0 | H28: B.Tech | I28: 96 | J28: 42 | K28: Offered | L28: Pending | N28: Recruiter D
A29: APP00028 | B29: 45969 | C29: Arjun Upadhyay | D29: IT | E29: Software Engineer | F29: Job Portal | G29: 10 | H29: B.Tech | I29: 92 | J29: 64 | K29: Hired | L29: Accepted | M29: 30 | N29: Recruiter C
A30: APP00029 | B30: 45804 | C30: Rohan Singh | D30: Sales | E30: Sales Manager | F30: Social Media | G30: 7 | H30: MCA | I30: 52 | J30: 65 | K30: Rejected | L30: N/A | N30: Recruiter B
A31: APP00030 | B31: 46088 | C31: Lakhan Joshi | D31: Marketing | E31: Content Strategist | F31: Consultancy | G31: 10 | H31: Graduate | I31: 58 | J31: 64 | K31: Interviewed | L31: N/A | N31: Recruiter A
A32: APP00031 | B32: 45696 | C32: Aman Rao | D32: IT | E32: Software Engineer | F32: Job Portal | G32: 9 | H32: B.Tech | I32: 48 | J32: 73 | K32: Rejected | L32: N/A | N32: Recruiter D
A33: APP00032 | B33: 45661 | C33: Aditi Patel | D33: R&D | E33: Research Analyst | F33: Campus | G33: 12 | H33: MCA | I33: 64 | J33: 94 | K33: Rejected | L33: N/A | N33: Recruiter B
A34: APP00033 | B34: 45724 | C34: Lakhan Patel | D34: Operations | E34: Process Analyst | F34: Campus | G34: 5 | H34: MCA | I34: 79 | J34: 96 | K34: Rejected | L34: N/A | N34: Recruiter A
A35: APP00034 | B35: 45708 | C35: Sara Nair | D35: Logistics | E35: Supply Chain Analyst | F35: Job Portal | G35: 4 | H35: Post Graduate | I35: 90 | J35: 54 | K35: Offered | L35: Pending | N35: Recruiter D
A36: APP00035 | B36: 46204 | C36: Aryan Kumar | D36: Customer Support | E36: Support Manager | F36: Social Media | G36: 10 | H36: MCA | I36: 46 | J36: 72 | K36: Hired | L36: Accepted | M36: 15 | N36: Recruiter D
A37: APP00036 | B37: 46015 | C37: Kabir Das | D37: R&D | E37: Research Analyst | F37: Consultancy | G37: 12 | H37: Graduate | I37: 81 | J37: 59 | K37: Hired | L37: Accepted | M37: 54 | N37: Recruiter C
A38: APP00037 | B38: 45748 | C38: Rohan Rao | D38: Marketing | E38: Marketing Executive | F38: Job Portal | G38: 0 | H38: Other | I38: 67 | J38: 83 | K38: Interviewed | L38: N/A | N38: Recruiter E
A39: APP00038 | B39: 45865 | C39: Aryan Gupta | D39: Customer Support | E39: Service Executive | F39: Campus | G39: 9 | H39: B.Tech | I39: 73 | J39: 79 | K39: Interviewed | L39: N/A | N39: Recruiter A
A40: APP00039 | B40: 46090 | C40: Ram Kapoor | D40: Sales | E40: Sales Manager | F40: Social Media | G40: 9 | H40: Graduate | I40: 59 | J40: 70 | K40: Rejected | L40: N/A | N40: Recruiter A
A41: APP00040 | B41: 46095 | C41: Pooja Sethi | D41: Customer Support | E41: Service Executive | F41: Employee Referral | G41: 7 | H41: Other | I41: 89 | J41: 95 | K41: Applied | L41: N/A | N41: Recruiter B
A42: APP00041 | B42: 46076 | C42: Govind Kapoor | D42: R&D | E42: Research Engineer | F42: Job Portal | G42: 3 | H42: Graduate | I42: 72 | J42: 74 | K42: Interviewed | L42: N/A | N42: Recruiter D
A43: APP00042 | B43: 46069 | C43: Sara Nair | D43: Finance | E43: Payroll Analyst | F43: Employee Referral | G43: 2 | H43: B.Tech | I43: 82 | J43: 50 | K43: Applied | L43: N/A | N43: Recruiter E
A44: APP00043 | B44: 45857 | C44: Aditya Tiwari | D44: IT | E44: UI/UX Designer | F44: LinkedIn | G44: 7 | H44: Post Graduate | I44: 86 | J44: 65 | K44: Applied | L44: N/A | N44: Recruiter E
A45: APP00044 | B45: 46132 | C45: Vihaan Upadhyay | D45: Logistics | E45: Logistics Executive | F45: Campus | G45: 4 | H45: Graduate | I45: 82 | J45: 77 | K45: Applied | L45: N/A | N45: Recruiter B
A46: APP00045 | B46: 46146 | C46: Satyam Sethi | D46: Operations | E46: Process Analyst | F46: Employee Referral | G46: 7 | H46: Diploma | I46: 74 | J46: 49 | K46: Screened | L46: N/A | N46: Recruiter A
A47: APP00046 | B47: 46228 | C47: Aarav Verma | D47: R&D | E47: Research Engineer | F47: Social Media | G47: 5 | H47: Diploma | I47: 92 | J47: 74 | K47: Applied | L47: N/A | N47: Recruiter A
A48: APP00047 | B48: 46054 | C48: Aman Verma | D48: Administration | E48: Admin Executive | F48: Consultancy | G48: 5 | H48: Post Graduate | I48: 75 | J48: 75 | K48: Interviewed | L48: N/A | N48: Recruiter E
A49: APP00048 | B49: 46017 | C49: Arjun Gupta | D49: Operations | E49: Operations Analyst | F49: Consultancy | G49: 12 | H49: Diploma | I49: 50 | J49: 74 | K49: Interviewed | L49: N/A | N49: Recruiter E
... A59: APP00058 | B59: 46039 | C59: Kabir Malhotra | D59: Sales | E59: Business Development Executive | F59: Social Media | G59: 3 | H59: MBA | I59: 61 | J59: 61 | K59: Offered | L59: Pending | N59: Recruiter E
A60: APP00059 | B60: 46020 | C60: Rahul Joshi | D60: R&D | E60: Innovation Analyst | F60: Consultancy | G60: 8 | H60: Diploma | I60: 57 | J60: 82 | K60: Hired | L60: Accepted | M60: 27 | N60: Recruiter E
A61: APP00060 | B61: 46218 | C61: Arun Sethi | D61: Marketing | E61: Content Strategist | F61: LinkedIn | G61: 6 | H61: MBA | I61: 85 | J61: 50 | K61: Rejected | L61: N/A | N61: Recruiter D
A62: APP00061 | B62: 45978 | C62: Divyansh Das | D62: Sales | E62: Sales Analyst | F62: Employee Referral | G62: 3 | H62: Diploma | I62: 54 | J62: 41 | K62: Rejected | L62: N/A | N62: Recruiter E
A63: APP00062 | B63: 46178 | C63: Neha Nair | D63: Administration | E63: Admin Executive | F63: Consultancy | G63: 9 | H63: Other | I63: 63 | J63: 55 | K63: Applied | L63: N/A | N63: Recruiter E
A64: APP00063 | B64: 45915 | C64: Sara Dwivedi | D64: R&D | E64: Research Engineer | F64: Social Media | G64: 4 | H64: Diploma | I64: 60 | J64: 95 | K64: Rejected | L64: N/A | N64: Recruiter E
A65: APP00064 | B65: 45682 | C65: Divyansh Singh | D65: IT | E65: QA Engineer | F65: Company Website | G65: 12 | H65: MCA | I65: 91 | J65: 90 | K65: Screened | L65: N/A | N65: Recruiter A
A66: APP00065 | B66: 46202 | C66: Arun Sharma | D66: Logistics | E66: Supply Chain Analyst | F66: Job Portal | G66: 4 | H66: MBA | I66: 70 | J66: 69 | K66: Applied | L66: N/A | N66: Recruiter B
A67: APP00066 | B67: 46275 | C67: Yash Das | D67: Sales | E67: Sales Manager | F67: LinkedIn | G67: 12 | H67: MCA | I67: 57 | J67: 76 | K67: Applied | L67: N/A | N67: Recruiter D
A68: APP00067 | B68: 45980 | C68: Govind Sharma | D68: Finance | E68: Auditor | F68: LinkedIn | G68: 4 | H68: B.Tech | I68: 85 | J68: 90 | K68: Rejected | L68: N/A | N68: Recruiter A
A69: APP00068 | B69: 45799 | C69: Aditi Kumar | D69: HR | E69: HR Manager | F69: Social Media | G69: 5 | H69: MCA | I69: 80 | J69: 62 | K69: Applied | L69: N/A | N69: Recruiter A
A70: APP00069 | B70: 45681 | C70: Rohan Tiwari | D70: Sales | E70: Business Development Executive | F70: LinkedIn | G70: 10 | H70: Graduate | I70: 56 | J70: 75 | K70: Applied | L70: N/A | N70: Recruiter B
A71: APP00070 | B71: 45896 | C71: Arun Tiwari | D71: Administration | E71: Admin Assistant | F71: LinkedIn | G71: 3 | H71: Graduate | I71: 93 | J71: 71 | K71: Interviewed | L71: N/A | N71: Recruiter A
A72: APP00071 | B72: 45902 | C72: Karan Patel | D72: HR | E72: Recruiter | F72: Employee Referral | G72: 10 | H72: Diploma | I72: 67 | J72: 76 | K72: Applied | L72: N/A | N72: Recruiter B
... A89: APP00088 | B89: 46153 | C89: Aarav Nair | D89: Logistics | E89: Transport Coordinator | F89: LinkedIn | G89: 1 | H89: MCA | I89: 88 | J89: 81 | K89: Applied | L89: N/A | N89: Recruiter E
A90: APP00089 | B90: 46277 | C90: Divyansh Verma | D90: HR | E90: HR Manager | F90: Employee Referral | G90: 2 | H90: Post Graduate | I90: 69 | J90: 97 | K90: Hired | L90: Accepted | M90: 31 | N90: Recruiter B
A91: APP00090 | B91: 46095 | C91: Aditi Chauhan | D91: R&D | E91: Research Analyst | F91: Employee Referral | G91: 2 | H91: Post Graduate | I91: 88 | J91: 79 | K91: Applied | L91: N/A | N91: Recruiter E
A92: APP00091 | B92: 45758 | C92: Neha Verma | D92: Finance | E92: Accountant | F92: Consultancy | G92: 9 | H92: Diploma | I92: 80 | J92: 55 | K92: Screened | L92: N/A | N92: Recruiter D
A93: APP00092 | B93: 46103 | C93: Aryan Upadhyay | D93: Marketing | E93: Brand Manager | F93: Campus | G93: 12 | H93: MCA | I93: 75 | J93: 47 | K93: Hired | L93: Accepted | M93: 32 | N93: Recruiter D
A94: APP00093 | B94: 46110 | C94: Ram Dwivedi | D94: Administration | E94: Admin Executive | F94: Consultancy | G94: 10 | H94: MCA | I94: 63 | J94: 62 | K94: Rejected | L94: N/A | N94: Recruiter A
A95: APP00094 | B95: 45715 | C95: Divyansh Patel | D95: Operations | E95: Operations Manager | F95: Job Portal | G95: 4 | H95: Post Graduate | I95: 62 | J95: 60 | K95: Applied | L95: N/A | N95: Recruiter D
A96: APP00095 | B96: 46231 | C96: Rohan Mehta | D96: R&D | E96: Research Engineer | F96: Social Media | G96: 7 | H96: Diploma | I96: 80 | J96: 79 | K96: Applied | L96: N/A | N96: Recruiter A
A97: APP00096 | B97: 45981 | C97: Ishita Singh | D97: Finance | E97: Auditor | F97: Company Website | G97: 8 | H97: Graduate | I97: 70 | J97: 68 | K97: Hired | L97: Accepted | M97: 13 | N97: Recruiter E
A98: APP00097 | B98: 46075 | C98: Meera Verma | D98: Marketing | E98: Content Strategist | F98: Campus | G98: 10 | H98: MCA | I98: 89 | J98: 69 | K98: Offered | L98: Pending | N98: Recruiter B
A99: APP00098 | B99: 46212 | C99: Ishita Mishra | D99: Marketing | E99: Brand Manager | F99: Social Media | G99: 8 | H99: Post Graduate | I99: 51 | J99: 42 | K99: Applied | L99: N/A | N99: Recruiter D
A100: APP00099 | B100: 45707 | C100: Kabir Malhotra | D100: Finance | E100: Financial Analyst | F100: Job Portal | G100: 12 | H100: Graduate | I100: 65 | J100: 46 | K100: Applied | L100: N/A | N100: Recruiter E
A101: APP00100 | B101: 45810 | C101: Riya Patel | D101: Sales | E101: Sales Manager | F101: Company Website | G101: 0 | H101: Other | I101: 51 | J101: 55 | K101: Interviewed | L101: N/A | N101: Recruiter B
A102: APP00101 | B102: 46221 | C102: Aditya Chauhan | D102: Finance | E102: Financial Analyst | F102: Job Portal | G102: 11 | H102: MCA | I102: 57 | J102: 83 | K102: Hired | L102: Accepted | M102: 53 | N102: Recruiter D
A103: APP00102 | B103: 45667 | C103: Govind Verma | D103: Marketing | E103: Brand Manager | F103: Social Media | G103: 3 | H103: MCA | I103: 79 | J103: 76 | K103: Offered | L103: Pending | N103: Recruiter D
A104: APP00103 | B104: 46272 | C104: Rinku Mehta | D104: Marketing | E104: Brand Manager | F104: Social Media | G104: 0 | H104: MBA | I104: 74 | J104: 87 | K104: Interviewed | L104: N/A | N104: Recruiter D
A105: APP00104 | B105: 45705 | C105: Kabir Gupta | D105: Administration | E105: Office Manager | F105: Consultancy | G105: 0 | H105: Graduate | I105: 46 | J105: 62 | K105: Applied | L105: N/A | N105: Recruiter D
A106: APP00105 | B106: 45774 | C106: Karan Sharma | D106: IT | E106: DevOps Engineer | F106: Consultancy | G106: 6 | H106: MCA | I106: 60 | J106: 57 | K106: Interviewed | L106: N/A | N106: Recruiter E
A107: APP00106 | B107: 45764 | C107: Nisha Verma | D107: Logistics | E107: Warehouse Manager | F107: Consultancy | G107: 2 | H107: Graduate | I107: 58 | J107: 69 | K107: Applied | L107: N/A | N107: Recruiter E
A108: APP00107 | B108: 45929 | C108: Vikram Kapoor | D108: HR | E108: Payroll Executive | F108: Employee Referral | G108: 12 | H108: B.Tech | I108: 86 | J108: 59 | K108: Screened | L108: N/A | N108: Recruiter D
A109: APP00108 | B109: 46062 | C109: Satyam Patel | D109: Finance | E109: Auditor | F109: Employee Referral | G109: 5 | H109: MBA | I109: 66 | J109: 64 | K109: Rejected | L109: N/A | N109: Recruiter D
A110: APP00109 | B110: 46107 | C110: Rinku Chauhan | D110: HR | E110: Recruiter | F110: Campus | G110: 7 | H110: MBA | I110: 91 | J110: 83 | K110: Rejected | L110: N/A | N110: Recruiter B
A111: APP00110 | B111: 46256 | C111: Aditya Malhotra | D111: Customer Support | E111: Support Manager | F111: Consultancy | G111: 5 | H111: MBA | I111: 70 | J111: 46 | K111: Applied | L111: N/A | N111: Recruiter E
A112: APP00111 | B112: 46039 | C112: Rohan Mishra | D112: Marketing | E112: Marketing Executive | F112: Consultancy | G112: 5 | H112: Other | I112: 76 | J112: 53 | K112: Interviewed | L112: N/A | N112: Recruiter E
A113: APP00112 | B113: 45705 | C113: Anshul Mehta | D113: Administration | E113: Admin Assistant | F113: Social Media | G113: 2 | H113: MBA | I113: 91 | J113: 48 | K113: Applied | L113: N/A | N113: Recruiter A
A114: APP00113 | B114: 46058 | C114: Ram Joshi | D114: Sales | E114: Business Development Executive | F114: Job Portal | G114: 6 | H114: Diploma | I114: 56 | J114: 71 | K114: Screened | L114: N/A | N114: Recruiter A
A115: APP00114 | B115: 46084 | C115: Anshul Gupta | D115: HR | E115: HR Manager | F115: Company Website | G115: 12 | H115: Post Graduate | I115: 51 | J115: 83 | K115: Screened | L115: N/A | N115: Recruiter C
A116: APP00115 | B116: 45773 | C116: Neha Nair | D116: R&D | E116: Research Engineer | F116: Company Website | G116: 9 | H116: MBA | I116: 70 | J116: 74 | K116: Hired | L116: Accepted | M116: 23 | N116: Recruiter A
A117: APP00116 | B117: 45978 | C117: Rahul Sethi | D117: Sales | E117: Account Manager | F117: Job Portal | G117: 6 | H117: Post Graduate | I117: 79 | J117: 76 | K117: Screened | L117: N/A | N117: Recruiter D
A118: APP00117 | B118: 45661 | C118: Govind Dwivedi | D118: R&D | E118: Research Engineer | F118: Social Media | G118: 0 | H118: Post Graduate | I118: 62 | J118: 74 | K118: Applied | L118: N/A | N118: Recruiter D
A119: APP00118 | B119: 46010 | C119: Lakhan Dwivedi | D119: Marketing | E119: Marketing Executive | F119: Job Portal | G119: 9 | H119: MCA | I119: 56 | J119: 87 | K119: Rejected | L119: N/A | N119: Recruiter B
A120: APP00119 | B120: 46050 | C120: Aditi Khan | D120: Administration | E120: Admin Executive | F120: Job Portal | G120: 5 | H120: MBA | I120: 83 | J120: 54 | K120: Screened | L120: N/A | N120: Recruiter B
A121: APP00120 | B121: 45741 | C121: Diya Khan | D121: Logistics | E121: Logistics Executive | F121: Employee Referral | G121: 8 | H121: Graduate | I121: 73 | J121: 50 | K121: Applied | L121: N/A | N121: Recruiter E
A122: APP00121 | B122: 45747 | C122: Lakhan Malhotra | D122: Marketing | E122: Marketing Executive | F122: Social Media | G122: 8 | H122: Graduate | I122: 52 | J122: 68 | K122: Offered | L122: Pending | N122: Recruiter D
A123: APP00122 | B123: 46196 | C123: Rahul Khan | D123: Operations | E123: Operations Analyst | F123: Consultancy | G123: 9 | H123: B.Tech | I123: 91 | J123: 90 | K123: Rejected | L123: N/A | N123: Recruiter D
A124: APP00123 | B124: 46117 | C124: Vikram Kumar | D124: Sales | E124: Sales Analyst | F124: Job Portal | G124: 9 | H124: MBA | I124: 83 | J124: 43 | K124: Screened | L124: N/A | N124: Recruiter A
A125: APP00124 | B125: 46217 | C125: Nisha Chauhan | D125: HR | E125: Training Specialist | F125: Social Media | G125: 6 | H125: Graduate | I125: 95 | J125: 61 | K125: Rejected | L125: N/A | N125: Recruiter E
A126: APP00125 | B126: 45667 | C126: Divyansh Tiwari | D126: Logistics | E126: Logistics Executive | F126: Employee Referral | G126: 6 | H126: Other | I126: 49 | J126: 71 | K126: Applied | L126: N/A | N126: Recruiter B
A127: APP00126 | B127: 45862 | C127: Nisha Kapoor | D127: HR | E127: HR Manager | F127: Employee Referral | G127: 1 | H127: Other | I127: 55 | J127: 78 | K127: Interviewed | L127: N/A | N127: Recruiter B
A128: APP00127 | B128: 46086 | C128: Pooja Mishra | D128: Customer Support | E128: Support Executive | F128: Campus | G128: 9 | H128: Graduate | I128: 64 | J128: 78 | K128: Screened | L128: N/A | N128: Recruiter A
... A139: APP00138 | B139: 45897 | C139: Aditi Dwivedi | D139: Sales | E139: Business Development Executive | F139: LinkedIn | G139: 1 | H139: Graduate | I139: 65 | J139: 64 | K139: Applied | L139: N/A | N139: Recruiter D
A140: APP00139 | B140: 46191 | C140: Aditi Upadhyay | D140: Logistics | E140: Transport Coordinator | F140: Employee Referral | G140: 10 | H140: MCA | I140: 92 | J140: 61 | K140: Hired | L140: Accepted | M140: 49 | N140: Recruiter C
A141: APP00140 | B141: 45796 | C141: Riya Dwivedi | D141: Operations | E141: Operations Analyst | F141: Campus | G141: 10 | H141: Other | I141: 62 | J141: 98 | K141: Offered | L141: Pending | N141: Recruiter B
...

Sheet M4_Compensation
A1: Employee ID | B1: Employee Name | C1: Department | D1: Job Role | E1: Experience (Years) | F1: Monthly Salary | G1: Annual Salary | H1: Bonus % | I1: Annual Bonus | J1: Total Compensation | K1: Salary Grade | L1: Last Increment %
A2: EMP00001 | B2: Ram Gupta | C2: HR | D2: HR Executive | E2: 5.2 | F2: 46289 | G2: 555468 | H2: 9.5 | I2: 52769 | J2: 608237 | K2: G6 | L2: 13.5
A3: EMP00002 | B3: Rohan Rao | C3: R&D | D3: Research Analyst | E3: 7.4 | F3: 40280 | G3: 483360 | H3: 14.3 | I3: 69120 | J3: 552480 | K3: G4 | L3: 4.7
A4: EMP00003 | B4: Yash Upadhyay | C4: R&D | D4: Research Analyst | E4: 3 | F4: 56893 | G4: 682716 | H4: 11.9 | I4: 81243 | J4: 763959 | K4: G2 | L4: 4.8
A5: EMP00004 | B5: Aryan Joshi | C5: Sales | D5: Sales Executive | E5: 3.9 | F5: 64421 | G5: 773052 | H5: 14.9 | I5: 115185 | J5: 888237 | K5: G5 | L5: 12.4
A6: EMP00005 | B6: Karan Kapoor | C6: Operations | D6: Operations Executive | E6: 6.7 | F6: 75052 | G6: 900624 | H6: 14 | I6: 126087 | J6: 1026711 | K6: G2 | L6: 8.3
A7: EMP00006 | B7: Vikram Malhotra | C7: Logistics | D7: Warehouse Manager | E7: 1.7 | F7: 44361 | G7: 532332 | H7: 6.4 | I7: 34069 | J7: 566401 | K7: G1 | L7: 11.7
A8: EMP00007 | B8: Rinku Verma | C8: HR | D8: Payroll Executive | E8: 1.3 | F8: 53203 | G8: 638436 | H8: 11.7 | I8: 74697 | J8: 713133 | K8: G3 | L8: 5.4
A9: EMP00008 | B9: Karan Gupta | C9: IT | D9: System Administrator | E9: 6.9 | F9: 58512 | G9: 702144 | H9: 14 | I9: 98300 | J9: 800444 | K9: G2 | L9: 8.3
A10: EMP00009 | B10: Nisha Joshi | C10: Customer Support | D10: Customer Success Analyst | E10: 5.9 | F10: 76520 | G10: 918240 | H10: 5.9 | I10: 54176 | J10: 972416 | K10: G1 | L10: 8.2
A11: EMP00010 | B11: Yash Malhotra | C11: Sales | D11: Sales Executive | E11: 5 | F11: 49417 | G11: 593004 | H11: 10.5 | I11: 62265 | J11: 655269 | K11: G3 | L11: 13.6
A12: EMP00011 | B12: Arun Singh | C12: Sales | D12: Sales Analyst | E12: 7.1 | F12: 58021 | G12: 696252 | H12: 13.1 | I12: 91209 | J12: 787461 | K12: G3 | L12: 14.3
A13: EMP00012 | B13: Neha Tiwari | C13: Operations | D13: Operations Analyst | E13: 5.4 | F13: 102341 | G13: 1228092 | H13: 11 | I13: 135090 | J13: 1363182 | K13: G1 | L13: 5.9
... A501: EMP00500 | B501: Diya Dwivedi | C501: R&D | D501: Research Analyst | E501: 6.3 | F501: 112852 | G501: 1354224 | H501: 13.1 | I501: 177403 | J501: 1531627 | K501: G3 | L501: 14.3

Sheet M5_Workforce_Planning
A1: Plan ID | B1: Year | C1: Department | D1: Job Role | E1: Current Headcount | F1: Required Headcount | G1: Projected Demand | H1: Current Gap | I1: Projected Gap | J1: Critical Skill | K1: Skill Gap % | L1: Hiring Priority | M1: Attrition Forecast % | N1: Training Need
A2: PLAN0001 | B2: 2029 | C2: R&D | D2: Innovation Analyst | E2: 22 | F2: 24 | G2: 32 | H2: 2 | I2: 10 | J2: Digital Marketing | K2: 41 | L2: High | M2: 17.3 | N2: Medium
A3: PLAN0002 | B3: 2026 | C3: Sales | D3: Sales Analyst | E3: 68 | F3: 81 | G3: 101 | H3: 13 | I3: 33 | J3: Cloud Computing | K3: 29 | L3: High | M3: 4.5 | N3: Critical
A4: PLAN0003 | B4: 2028 | C4: Finance | D4: Finance Manager | E4: 51 | F4: 55 | G4: 57 | H4: 4 | I4: 6 | J4: Sales Strategy | K4: 12 | L4: High | M4: 11.2 | N4: Medium
A5: PLAN0004 | B5: 2026 | C5: Customer Support | D5: Customer Success Analyst | E5: 22 | F5: 25 | G5: 39 | H5: 3 | I5: 17 | J5: Digital Marketing | K5: 12 | L5: Low | M5: 6.9 | N5: Critical
A6: PLAN0005 | B6: 2026 | C6: Customer Support | D6: Customer Success Analyst | E6: 58 | F6: 67 | G6: 84 | H6: 9 | I6: 26 | J6: Project Management | K6: 21 | L6: High | M6: 12.5 | N6: Low
A7: PLAN0006 | B7: 2027 | C7: IT | D7: Data Analyst | E7: 61 | F7: 67 | G7: 85 | H7: 6 | I7: 24 | J7: Digital Marketing | K7: 33 | L7: Medium | M7: 8.4 | N7: Critical
A8: PLAN0007 | B8: 2030 | C8: HR | D8: Recruiter | E8: 15 | F8: 18 | G8: 27 | H8: 3 | I8: 12 | J8: Sales Strategy | K8: 43 | L8: Medium | M8: 12.6 | N8: High
A9: PLAN0008 | B9: 2027 | C9: HR | D9: Training Specialist | E9: 50 | F9: 63 | G9: 67 | H9: 13 | I9: 17 | J9: Cloud Computing | K9: 12 | L9: Low | M9: 17.7 | N9: Low
A10: PLAN0009 | B10: 2026 | C10: Marketing | D10: Digital Marketing Analyst | E10: 53 | F10: 67 | G10: 74 | H10: 14 | I10: 21 | J10: Cyber Security | K10: 42 | L10: Low | M10: 5.4 | N10: Critical
A11: PLAN0010 | B11: 2026 | C11: Customer Support | D11: Service Executive | E11: 27 | F11: 30 | G11: 30 | H11: 3 | I11: 3 | J11: Cloud Computing | K11: 36 | L11: High | M11: 17.2 | N11: Low
A12: PLAN0011 | B12: 2028 | C12: Marketing | D12: SEO Specialist | E12: 57 | F12: 68 | G12: 84 | H12: 11 | I12: 27 | J12: Communication | K12: 42 | L12: Medium | M12: 12.1 | N12: Critical
A13: PLAN0012 | B13: 2028 | C13: R&D | D13: Research Engineer | E13: 59 | F13: 72 | G13: 87 | H13: 13 | I13: 28 | J13: Sales Strategy | K13: 22 | L13: High | M13: 5.5 | N13: High
... A301: PLAN0300 | B301: 2027 | C301: Finance | D301: Accountant | E301: 29 | F301: 30 | G301: 43 | H301: 1 | I301: 14 | J301: Data Analytics | K301: 6 | L301: Low | M301: 13.7 | N301: Medium

Sheet Dashboard_Data
A1: Dashboard helper calculations — source module edits drive these formulas.
A3: Department | B3: Avg Performance | D3: Rating | E3: Count | G3: Top Employee | H3: Department | I3: Score
A4: IT | B4: =IFERROR(AVERAGEIF(M1_Performance!C:C,A4,M1_Performance!G:G),0) -> 3.7145 | D4: Excellent | E4: =COUNTIF(M1_Performance!L:L,D4) -> 98 | G4: =INDEX(M1_Performance!B:B,MATCH(I4,M1_Performance!G:G,0)) -> Divyansh Joshi | H4: =INDEX(M1_Performance!C:C,MATCH(I4,M1_Performance!G:G,0)) -> Administration | I4: =LARGE(M1_Performance!G:G,1) -> 5
A5: HR | B5: =IFERROR(AVERAGEIF(M1_Performance!C:C,A5,M1_Performance!G:G),0) -> 3.6378333 | D5: Very Good | E5: =COUNTIF(M1_Performance!L:L,D5) -> 103 | G5: =INDEX(M1_Performance!B:B,MATCH(I5,M1_Performance!G:G,0)) -> Ananya Singh | H5: =INDEX(M1_Performance!C:C,MATCH(I5,M1_Performance!G:G,0)) -> Sales | I5: =LARGE(M1_Performance!G:G,2) -> 4.99
A6: Finance | B6: =IFERROR(AVERAGEIF(M1_Performance!C:C,A6,M1_Performance!G:G),0) -> 3.5989362 | D6: Good | E6: =COUNTIF(M1_Performance!L:L,D6) -> 109 | G6: =INDEX(M1_Performance!B:B,MATCH(I6,M1_Performance!G:G,0)) -> Ananya Singh | H6: =INDEX(M1_Performance!C:C,MATCH(I6,M1_Performance!G:G,0)) -> Sales | I6: =LARGE(M1_Performance!G:G,3) -> 4.99
A7: Sales | B7: =IFERROR(AVERAGEIF(M1_Performance!C:C,A7,M1_Performance!G:G),0) -> 3.4242 | D7: Average | E7: =COUNTIF(M1_Performance!L:L,D7) -> 99 | G7: =INDEX(M1_Performance!B:B,MATCH(I7,M1_Performance!G:G,0)) -> Ananya Singh | H7: =INDEX(M1_Performance!C:C,MATCH(I7,M1_Performance!G:G,0)) -> Sales | I7: =LARGE(M1_Performance!G:G,4) -> 4.99
A8: Marketing | B8: =IFERROR(AVERAGEIF(M1_Performance!C:C,A8,M1_Performance!G:G),0) -> 3.4623913 | D8: Needs Improvement | E8: =COUNTIF(M1_Performance!L:L,D8) -> 91 | G8: =INDEX(M1_Performance!B:B,MATCH(I8,M1_Performance!G:G,0)) -> Aarav Gupta | H8: =INDEX(M1_Performance!C:C,MATCH(I8,M1_Performance!G:G,0)) -> Sales | I8: =LARGE(M1_Performance!G:G,5) -> 4.97
A9: Operations | B9: =IFERROR(AVERAGEIF(M1_Performance!C:C,A9,M1_Performance!G:G),0) -> 3.6955102
A10: R&D | B10: =IFERROR(AVERAGEIF(M1_Performance!C:C,A10,M1_Performance!G:G),0) -> 3.6291803
A11: Administration | B11: =IFERROR(AVERAGEIF(M1_Performance!C:C,A11,M1_Performance!G:G),0) -> 3.5964151
A12: Logistics | B12: =IFERROR(AVERAGEIF(M1_Performance!C:C,A12,M1_Performance!G:G),0) -> 3.6370213
A13: Department | B13: Attrition Rate | D13: Status | E13: Count | G13: Risk Employee | H13: Department | I13: Risk
A14: IT | B14: =IFERROR(COUNTIFS(M2_Attrition!C:C,A14,M2_Attrition!L:L,"Exited")/COUNTIF(M2_Attrition!C:C,A14),0) -> 0.125 | D14: Active | E14: =COUNTIF(M2_Attrition!L:L,D14) -> 451 | G14: =INDEX(M2_Attrition!B:B,MATCH(J14,M2_Attrition!I:I,0)) -> Ishita Kumar | H14: =INDEX(M2_Attrition!C:C,MATCH(J14,M2_Attrition!I:I,0)) -> R&D | I14: =IF(J14<=2,"High",IF(J14<=3,"Medium","Low")) -> High | J14: =SMALL(M2_Attrition!I:I,1) -> 1
A15: HR | B15: =IFERROR(COUNTIFS(M2_Attrition!C:C,A15,M2_Attrition!L:L,"Exited")/COUNTIF(M2_Attrition!C:C,A15),0) -> 0.1 | D15: Exited | E15: =COUNTIF(M2_Attrition!L:L,D15) -> 49 | G15: =INDEX(M2_Attrition!B:B,MATCH(J15,M2_Attrition!I:I,0)) -> Ishita Kumar | H15: =INDEX(M2_Attrition!C:C,MATCH(J15,M2_Attrition!I:I,0)) -> R&D | I15: =IF(J15<=2,"High",IF(J15<=3,"Medium","Low")) -> High | J15: =SMALL(M2_Attrition!I:I,2) -> 1
A16: Finance | B16: =IFERROR(COUNTIFS(M2_Attrition!C:C,A16,M2_Attrition!L:L,"Exited")/COUNTIF(M2_Attrition!C:C,A16),0) -> 0.12765957 | G16: =INDEX(M2_Attrition!B:B,MATCH(J16,M2_Attrition!I:I,0)) -> Ishita Kumar | H16: =INDEX(M2_Attrition!C:C,MATCH(J16,M2_Attrition!I:I,0)) -> R&D | I16: =IF(J16<=2,"High",IF(J16<=3,"Medium","Low")) -> High | J16: =SMALL(M2_Attrition!I:I,3) -> 1
A17: Sales | B17: =IFERROR(COUNTIFS(M2_Attrition!C:C,A17,M2_Attrition!L:L,"Exited")/COUNTIF(M2_Attrition!C:C,A17),0) -> 0.04 | G17: =INDEX(M2_Attrition!B:B,MATCH(J17,M2_Attrition!I:I,0)) -> Ishita Kumar | H17: =INDEX(M2_Attrition!C:C,MATCH(J17,M2_Attrition!I:I,0)) -> R&D | I17: =IF(J17<=2,"High",IF(J17<=3,"Medium","Low")) -> High | J17: =SMALL(M2_Attrition!I:I,4) -> 1
A18: Marketing | B18: =IFERROR(COUNTIFS(M2_Attrition!C:C,A18,M2_Attrition!L:L,"Exited")/COUNTIF(M2_Attrition!C:C,A18),0) -> 0.086956522 | G18: =INDEX(M2_Attrition!B:B,MATCH(J18,M2_Attrition!I:I,0)) -> Ishita Kumar | H18: =INDEX(M2_Attrition!C:C,MATCH(J18,M2_Attrition!I:I,0)) -> R&D | I18: =IF(J18<=2,"High",IF(J18<=3,"Medium","Low")) -> High | J18: =SMALL(M2_Attrition!I:I,5) -> 1
A19: Operations | B19: =IFERROR(COUNTIFS(M2_Attrition!C:C,A19,M2_Attrition!L:L,"Exited")/COUNTIF(M2_Attrition!C:C,A19),0) -> 0.14285714
A20: R&D | B20: =IFERROR(COUNTIFS(M2_Attrition!C:C,A20,M2_Attrition!L:L,"Exited")/COUNTIF(M2_Attrition!C:C,A20),0) -> 0.06557377
A21: Administration | B21: =IFERROR(COUNTIFS(M2_Attrition!C:C,A21,M2_Attrition!L:L,"Exited")/COUNTIF(M2_Attrition!C:C,A21),0) -> 0.16981132
A22: Logistics | B22: =IFERROR(COUNTIFS(M2_Attrition!C:C,A22,M2_Attrition!L:L,"Exited")/COUNTIF(M2_Attrition!C:C,A22),0) -> 0.063829787
A23: Customer Support | B23: =IFERROR(COUNTIFS(M2_Attrition!C:C,A23,M2_Attrition!L:L,"Exited")/COUNTIF(M2_Attrition!C:C,A23),0) -> 0.063829787
A24: Source | B24: Hires | D24: Stage | E24: Applications | G24: Month | H24: Hires | J24: Department | K24: Avg Days
A25: Job Portal | B25: =COUNTIFS(M3_Recruitment!F:F,A25,M3_Recruitment!K:K,"Hired") -> 7 | D25: Applied | E25: =COUNTIF(M3_Recruitment!K:K,D25) -> 136 | G25: =DATE(YEAR(TODAY()),1,1) -> 46023 | H25: =COUNTIFS(M3_Recruitment!B:B,">="&G25,M3_Recruitment!B:B,"<"&EDATE(G25,1),M3_Recruitment!K:K,"Hired") -> 4 | J25: IT | K25: =IFERROR(AVERAGEIF(M3_Recruitment!D:D,J25,M3_Recruitment!M:M),0) -> 28
A26: Campus | B26: =COUNTIFS(M3_Recruitment!F:F,A26,M3_Recruitment!K:K,"Hired") -> 6 | D26: Screened | E26: =COUNTIF(M3_Recruitment!K:K,D26) -> 92 | G26: =DATE(YEAR(TODAY()),2,1) -> 46054 | H26: =COUNTIFS(M3_Recruitment!B:B,">="&G26,M3_Recruitment!B:B,"<"&EDATE(G26,1),M3_Recruitment!K:K,"Hired") -> 1 | J26: HR | K26: =IFERROR(AVERAGEIF(M3_Recruitment!D:D,J26,M3_Recruitment!M:M),0) -> 31.666667
A27: Employee Referral | B27: =COUNTIFS(M3_Recruitment!F:F,A27,M3_Recruitment!K:K,"Hired") -> 6 | D27: Interviewed | E27: =COUNTIF(M3_Recruitment!K:K,D27) -> 76 | G27: =DATE(YEAR(TODAY()),3,1) -> 46082 | H27: =COUNTIFS(M3_Recruitment!B:B,">="&G27,M3_Recruitment!B:B,"<"&EDATE(G27,1),M3_Recruitment!K:K,"Hired") -> 3 | J27: Finance | K27: =IFERROR(AVERAGEIF(M3_Recruitment!D:D,J27,M3_Recruitment!M:M),0) -> 26.333333
A28: Social Media | B28: =COUNTIFS(M3_Recruitment!F:F,A28,M3_Recruitment!K:K,"Hired") -> 9 | D28: Offered | E28: =COUNTIF(M3_Recruitment!K:K,D28) -> 47 | G28: =DATE(YEAR(TODAY()),4,1) -> 46113 | H28: =COUNTIFS(M3_Recruitment!B:B,">="&G28,M3_Recruitment!B:B,"<"&EDATE(G28,1),M3_Recruitment!K:K,"Hired") -> 2 | J28: Sales | K28: =IFERROR(AVERAGEIF(M3_Recruitment!D:D,J28,M3_Recruitment!M:M),0) -> 34
A29: LinkedIn | B29: =COUNTIFS(M3_Recruitment!F:F,A29,M3_Recruitment!K:K,"Hired") -> 3 | D29: Hired | E29: =COUNTIF(M3_Recruitment!K:K,D29) -> 42 | G29: =DATE(YEAR(TODAY()),5,1) -> 46143 | H29: =COUNTIFS(M3_Recruitment!B:B,">="&G29,M3_Recruitment!B:B,"<"&EDATE(G29,1),M3_Recruitment!K:K,"Hired") -> 3 | J29: Marketing | K29: =IFERROR(AVERAGEIF(M3_Recruitment!D:D,J29,M3_Recruitment!M:M),0) -> 40
A30: Company Website | B30: =COUNTIFS(M3_Recruitment!F:F,A30,M3_Recruitment!K:K,"Hired") -> 5 | D30: Rejected | E30: =COUNTIF(M3_Recruitment!K:K,D30) -> 107 | G30: =DATE(YEAR(TODAY()),6,1) -> 46174 | H30: =COUNTIFS(M3_Recruitment!B:B,">="&G30,M3_Recruitment!B:B,"<"&EDATE(G30,1),M3_Recruitment!K:K,"Hired") -> 3 | J30: Operations | K30: =IFERROR(AVERAGEIF(M3_Recruitment!D:D,J30,M3_Recruitment!M:M),0) -> 33.666667
A31: Consultancy | B31: =COUNTIFS(M3_Recruitment!F:F,A31,M3_Recruitment!K:K,"Hired") -> 6 | G31: =DATE(YEAR(TODAY()),7,1) -> 46204 | H31: =COUNTIFS(M3_Recruitment!B:B,">="&G31,M3_Recruitment!B:B,"<"&EDATE(G31,1),M3_Recruitment!K:K,"Hired") -> 3 | J31: R&D | K31: =IFERROR(AVERAGEIF(M3_Recruitment!D:D,J31,M3_Recruitment!M:M),0) -> 41.25
G32: =DATE(YEAR(TODAY()),8,1) -> 46235 | H32: =COUNTIFS(M3_Recruitment!B:B,">="&G32,M3_Recruitment!B:B,"<"&EDATE(G32,1),M3_Recruitment!K:K,"Hired") -> 1 | J32: Administration | K32: =IFERROR(AVERAGEIF(M3_Recruitment!D:D,J32,M3_Recruitment!M:M),0) -> 54
G33: =DATE(YEAR(TODAY()),9,1) -> 46266 | H33: =COUNTIFS(M3_Recruitment!B:B,">="&G33,M3_Recruitment!B:B,"<"&EDATE(G33,1),M3_Recruitment!K:K,"Hired") -> 1 | J33: Logistics | K33: =IFERROR(AVERAGEIF(M3_Recruitment!D:D,J33,M3_Recruitment!M:M),0) -> 40
G34: =DATE(YEAR(TODAY()),10,1) -> 46296 | H34: =COUNTIFS(M3_Recruitment!B:B,">="&G34,M3_Recruitment!B:B,"<"&EDATE(G34,1),M3_Recruitment!K:K,"Hired") -> 0 | J34: Customer Support | K34: =IFERROR(AVERAGEIF(M3_Recruitment!D:D,J34,M3_Recruitment!M:M),0) -> 27.25
G35: =DATE(YEAR(TODAY()),11,1) -> 46327 | H35: =COUNTIFS(M3_Recruitment!B:B,">="&G35,M3_Recruitment!B:B,"<"&EDATE(G35,1),M3_Recruitment!K:K,"Hired") -> 0
G36: =DATE(YEAR(TODAY()),12,1) -> 46357 | H36: =COUNTIFS(M3_Recruitment!B:B,">="&G36,M3_Recruitment!B:B,"<"&EDATE(G36,1),M3_Recruitment!K:K,"Hired") -> 0
A40: Salary Band | B40: Count | D40: Department | E40: Avg Compensation | G40: Year | H40: Avg Salary | J40: Top Paid | K40: Department | L40: Total Compensation
A41: < ₹30K | B41: =COUNTIFS(M4_Compensation!F:F,">=0",M4_Compensation!F:F,"<=29999") -> 11 | D41: IT | E41: =IFERROR(AVERAGEIF(M4_Compensation!C:C,D41,M4_Compensation!J:J),0) -> 1033209.6 | G41: 2022 | H41: =AVERAGE(M4_Compensation!F:F)*(1+(2022-2021)*0.04) -> 78919.221 | J41: =INDEX(M4_Compensation!B:B,MATCH(L41,M4_Compensation!J:J,0)) -> Yash Mishra | K41: =INDEX(M4_Compensation!C:C,MATCH(L41,M4_Compensation!J:J,0)) -> Sales | L41: =LARGE(M4_Compensation!J:J,1) -> 1730890
A42: ₹30K–₹50K | B42: =COUNTIFS(M4_Compensation!F:F,">=30000",M4_Compensation!F:F,"<=49999") -> 100 | D42: HR | E42: =IFERROR(AVERAGEIF(M4_Compensation!C:C,D42,M4_Compensation!J:J),0) -> 969716.08 | G42: 2023 | H42: =AVERAGE(M4_Compensation!F:F)*(1+(2023-2021)*0.04) -> 81954.575 | J42: =INDEX(M4_Compensation!B:B,MATCH(L42,M4_Compensation!J:J,0)) -> Vihaan Gupta | K42: =INDEX(M4_Compensation!C:C,MATCH(L42,M4_Compensation!J:J,0)) -> Administration | L42: =LARGE(M4_Compensation!J:J,2) -> 1719878
A43: ₹50K–₹80K | B43: =COUNTIFS(M4_Compensation!F:F,">=50000",M4_Compensation!F:F,"<=79999") -> 175 | D43: Finance | E43: =IFERROR(AVERAGEIF(M4_Compensation!C:C,D43,M4_Compensation!J:J),0) -> 965477.55 | G43: 2024 | H43: =AVERAGE(M4_Compensation!F:F)*(1+(2024-2021)*0.04) -> 84989.93 | J43: =INDEX(M4_Compensation!B:B,MATCH(L43,M4_Compensation!J:J,0)) -> Govind Mishra | K43: =INDEX(M4_Compensation!C:C,MATCH(L43,M4_Compensation!J:J,0)) -> Logistics | L43: =LARGE(M4_Compensation!J:J,3) -> 1708319
A44: ₹80K–₹1.2L | B44: =COUNTIFS(M4_Compensation!F:F,">=80000",M4_Compensation!F:F,"<=119999") -> 194 | D44: Sales | E44: =IFERROR(AVERAGEIF(M4_Compensation!C:C,D44,M4_Compensation!J:J),0) -> 1095747.1 | G44: 2025 | H44: =AVERAGE(M4_Compensation!F:F)*(1+(2025-2021)*0.04) -> 88025.285 | J44: =INDEX(M4_Compensation!B:B,MATCH(L44,M4_Compensation!J:J,0)) -> Neha Khan | K44: =INDEX(M4_Compensation!C:C,MATCH(L44,M4_Compensation!J:J,0)) -> Sales | L44: =LARGE(M4_Compensation!J:J,4) -> 1707232
A45: > ₹1.2L | B45: =COUNTIFS(M4_Compensation!F:F,">=120000",M4_Compensation!F:F,"<=9999999") -> 20 | D45: Marketing | E45: =IFERROR(AVERAGEIF(M4_Compensation!C:C,D45,M4_Compensation!J:J),0) -> 989649.37 | G45: 2026 | H45: =AVERAGE(M4_Compensation!F:F)*(1+(2026-2021)*0.04) -> 91060.639 | J45: =INDEX(M4_Compensation!B:B,MATCH(L45,M4_Compensation!J:J,0)) -> Sara Sharma | K45: =INDEX(M4_Compensation!C:C,MATCH(L45,M4_Compensation!J:J,0)) -> HR | L45: =LARGE(M4_Compensation!J:J,5) -> 1703253
D46: Operations | E46: =IFERROR(AVERAGEIF(M4_Compensation!C:C,D46,M4_Compensation!J:J),0) -> 953506.45
D47: R&D | E47: =IFERROR(AVERAGEIF(M4_Compensation!C:C,D47,M4_Compensation!J:J),0) -> 1004316
A48: Year | B48: Current HC | C48: Required HC | D48: Administration | E48: Skill | F48: Avg Gap | H48: Department | I48: Current | J48: Required | K48: Gap
A49: 2026 | B49: =SUMIF(M5_Workforce_Planning!B:B,A49,M5_Workforce_Planning!E:E) -> 2726 | C49: =SUMIF(M5_Workforce_Planning!B:B,A49,M5_Workforce_Planning!F:F) -> 3088 | D49: Logistics | E49: Data Analysis | F49: =IFERROR(AVERAGEIF(M5_Workforce_Planning!J:J,E49,M5_Workforce_Planning!K:K),0) -> 0 | H49: IT | I49: =SUMIF(M5_Workforce_Planning!C:C,H49,M5_Workforce_Planning!E:E) -> 1376 | J49: =SUMIF(M5_Workforce_Planning!C:C,H49,M5_Workforce_Planning!F:F) -> 1573 | K49: =J49-I49 -> 197
A50: 2027 | B50: =SUMIF(M5_Workforce_Planning!B:B,A50,M5_Workforce_Planning!E:E) -> 2985 | C50: =SUMIF(M5_Workforce_Planning!B:B,A50,M5_Workforce_Planning!F:F) -> 3383 | D50: Customer Support | E50: Cloud Computing | F50: =IFERROR(AVERAGEIF(M5_Workforce_Planning!J:J,E50,M5_Workforce_Planning!K:K),0) -> 24.361111 | H50: HR | I50: =SUMIF(M5_Workforce_Planning!C:C,H50,M5_Workforce_Planning!E:E) -> 1086 | J50: =SUMIF(M5_Workforce_Planning!C:C,H50,M5_Workforce_Planning!F:F) -> 1223 | K50: =J50-I50 -> 137
A51: 2028 | B51: =SUMIF(M5_Workforce_Planning!B:B,A51,M5_Workforce_Planning!E:E) -> 1763 | C51: =SUMIF(M5_Workforce_Planning!B:B,A51,M5_Workforce_Planning!F:F) -> 2066 | E51: Cyber Security | F51: =IFERROR(AVERAGEIF(M5_Workforce_Planning!J:J,E51,M5_Workforce_Planning!K:K),0) -> 28.166667 | H51: Finance | I51: =SUMIF(M5_Workforce_Planning!C:C,H51,M5_Workforce_Planning!E:E) -> 1713 | J51: =SUMIF(M5_Workforce_Planning!C:C,H51,M5_Workforce_Planning!F:F) -> 1934 | K51: =J51-I51 -> 221
A52: 2029 | B52: =SUMIF(M5_Workforce_Planning!B:B,A52,M5_Workforce_Planning!E:E) -> 2545 | C52: =SUMIF(M5_Workforce_Planning!B:B,A52,M5_Workforce_Planning!F:F) -> 2910 | E52: AI / ML | F52: =IFERROR(AVERAGEIF(M5_Workforce_Planning!J:J,E52,M5_Workforce_Planning!K:K),0) -> 28.944444 | H52: Sales | I52: =SUMIF(M5_Workforce_Planning!C:C,H52,M5_Workforce_Planning!E:E) -> 1273 | J52: =SUMIF(M5_Workforce_Planning!C:C,H52,M5_Workforce_Planning!F:F) -> 1545 | K52: =J52-I52 -> 272
A53: 2030 | B53: =SUMIF(M5_Workforce_Planning!B:B,A53,M5_Workforce_Planning!E:E) -> 2961 | C53: =SUMIF(M5_Workforce_Planning!B:B,A53,M5_Workforce_Planning!F:F) -> 3399 | E53: Project Management | F53: =IFERROR(AVERAGEIF(M5_Workforce_Planning!J:J,E53,M5_Workforce_Planning!K:K),0) -> 25.206897 | H53: Marketing | I53: =SUMIF(M5_Workforce_Planning!C:C,H53,M5_Workforce_Planning!E:E) -> 1181 | J53: =SUMIF(M5_Workforce_Planning!C:C,H53,M5_Workforce_Planning!F:F) -> 1373 | K53: =J53-I53 -> 192
H54: Operations | I54: =SUMIF(M5_Workforce_Planning!C:C,H54,M5_Workforce_Planning!E:E) -> 1299 | J54: =SUMIF(M5_Workforce_Planning!C:C,H54,M5_Workforce_Planning!F:F) -> 1466 | K54: =J54-I54 -> 167
H55: R&D | I55: =SUMIF(M5_Workforce_Planning!C:C,H55,M5_Workforce_Planning!E:E) -> 1190 | J55: =SUMIF(M5_Workforce_Planning!C:C,H55,M5_Workforce_Planning!F:F) -> 1355 | K55: =J55-I55 -> 165
H56: Administration | I56: =SUMIF(M5_Workforce_Planning!C:C,H56,M5_Workforce_Planning!E:E) -> 1237 | J56: =SUMIF(M5_Workforce_Planning!C:C,H56,M5_Workforce_Planning!F:F) -> 1420 | K56: =J56-I56 -> 183
H57: Logistics | I57: =SUMIF(M5_Workforce_Planning!C:C,H57,M5_Workforce_Planning!E:E) -> 1273 | J57: =SUMIF(M5_Workforce_Planning!C:C,H57,M5_Workforce_Planning!F:F) -> 1414 | K57: =J57-I57 -> 141
H58: Customer Support | I58: =SUMIF(M5_Workforce_Planning!C:C,H58,M5_Workforce_Planning!E:E) -> 1352 | J58: =SUMIF(M5_Workforce_Planning!C:C,H58,M5_Workforce_Planning!F:F) -> 1543 | K58: =J58-I58 -> 191

Sheet KPI CARD TABLE
D4: KPI CARDS TABLE
D7: TOTAL EMPLOYEE | E7: =COUNTA(M1_Performance!B2:B501) -> 500
D8: ATTRITION RATE | E8: =COUNTIF(M2_Attrition!L2:L501, "Exited") / COUNTA(M2_Attrition!A2:A501)*100 -> 9.8
D9: AVG PERFORMANCE SCORE | E9: =AVERAGE(M1_Performance!G2:G501) -> 3.60552
D10: AVG TIME TO HIRE | E10: =AVERAGE(M3_Recruitment!M2:M501) -> 35.452381
D11: AVG SALARY | E11: =AVERAGE(M4_Compensation!G2:G501) -> 910606.39
D12: TOTAL PAYROLL | E12: =SUM(M4_Compensation!J2:J501) -> 506209895
D13: WORKFORCE GAP | E13: =SUM(M5_Workforce_Planning!F2:F301)-SUM(M5_Workforce_Planning!E2:E301) -> 1866
